mass_driver_plugins/__init__.py
mass_driver_plugins/cli.py
mass_driver_plugins/jsonpatch.py
mass_driver_plugins/poetry_surgical.py
mass_driver_plugins/py.typed
mass_driver_plugins/surgical.py
mass_driver_plugins/template.py
mass_driver_plugins-0.5.1.dist-info/METADATA
mass_driver_plugins-0.5.1.dist-info/WHEEL
mass_driver_plugins-0.5.1.dist-info/entry_points.txt
mass_driver_plugins-0.5.1.dist-info/RECORD
