Metadata-Version: 2.1
Name: mass_driver_plugins
Version: 0.5.1
Summary: Experimental plugin ecosystem for Mass Driver
Author: Jb Doyon
Author-email: jb@jiby.tech
Requires-Python: >=3.11,<4.0
Classifier: Programming Language :: Python :: 3
Classifier: Programming Language :: Python :: 3.11
Classifier: Programming Language :: Python :: 3.12
Requires-Dist: Jinja2 (>=3.1.2,<4.0.0)
Requires-Dist: jsonpatch
Requires-Dist: jsonpointer
Requires-Dist: mass-driver (==0.20)
Requires-Dist: poetry-core
Requires-Dist: ruamel.yaml (>=0.17.21,<0.18.0)
Requires-Dist: tree-sitter (<0.22.0)
Requires-Dist: tree-sitter-languages
